md_browse/__init__.py
md_browse/clean.py
md_browse/converttomarkdown.py
md_browse/md_browse.py
md_browse-0.0.2.dist-info/LICENSE
md_browse-0.0.2.dist-info/METADATA
md_browse-0.0.2.dist-info/WHEEL
md_browse-0.0.2.dist-info/entry_points.txt
md_browse-0.0.2.dist-info/top_level.txt
md_browse-0.0.2.dist-info/RECORD
